hivaapcnt/__init__.py
hivaapcnt/hivaapcnt.py
hivaapcnt/data/__init__.py
hivaapcnt/data/allA.json
hivaapcnt/data/allAll.json
hivaapcnt/data/allB.json
hivaapcnt/data/allC.json
hivaapcnt/data/allCRF01_AE.json
hivaapcnt/data/allCRF02_AG.json
hivaapcnt/data/allD.json
hivaapcnt/data/allF.json
hivaapcnt/data/allG.json
hivaapcnt/data/allOther.json
hivaapcnt/data/artA.json
hivaapcnt/data/artAll.json
hivaapcnt/data/artB.json
hivaapcnt/data/artC.json
hivaapcnt/data/artCRF01_AE.json
hivaapcnt/data/artCRF02_AG.json
hivaapcnt/data/artD.json
hivaapcnt/data/artF.json
hivaapcnt/data/artG.json
hivaapcnt/data/artOther.json
hivaapcnt/data/naiveA.json
hivaapcnt/data/naiveAll.json
hivaapcnt/data/naiveB.json
hivaapcnt/data/naiveC.json
hivaapcnt/data/naiveCRF01_AE.json
hivaapcnt/data/naiveCRF02_AG.json
hivaapcnt/data/naiveD.json
hivaapcnt/data/naiveF.json
hivaapcnt/data/naiveG.json
hivaapcnt/data/naiveOther.json
hiv_aapcnt-2019.4.dist-info/METADATA
hiv_aapcnt-2019.4.dist-info/WHEEL
hiv_aapcnt-2019.4.dist-info/top_level.txt
hiv_aapcnt-2019.4.dist-info/zip-safe
hiv_aapcnt-2019.4.dist-info/RECORD
