Metadata-Version: 2.1
Name: hiv-aapcnt
Version: 2019.4
Summary: Amino acid prevalence data of HIV-1 pol
Home-page: https://github.com/hivdb/hiv-aapcnt/tree/master/hiv-aapcnt-python
Author: Philip Tzou
Author-email: philiptz@stanford.edu
License: UNKNOWN
Platform: UNKNOWN
Classifier: Development Status :: 4 - Beta
Classifier: Intended Audience :: Developers
Classifier: Intended Audience :: Science/Research
Classifier: License :: Public Domain
Classifier: Operating System :: OS Independent
Classifier: Programming Language :: Python
Classifier: Programming Language :: Python :: 3.6
Classifier: Programming Language :: Python :: 3.7
Classifier: Topic :: Scientific/Engineering :: Bio-Informatics
